langgraph/checkpoint/test_redis/__init__.py
langgraph/checkpoint/test_redis/aio.py
langgraph/checkpoint/test_redis/ashallow.py
langgraph/checkpoint/test_redis/base.py
langgraph/checkpoint/test_redis/jsonplus_redis.py
langgraph/checkpoint/test_redis/key_registry.py
langgraph/checkpoint/test_redis/message_exporter.py
langgraph/checkpoint/test_redis/py.typed
langgraph/checkpoint/test_redis/shallow.py
langgraph/checkpoint/test_redis/types.py
langgraph/checkpoint/test_redis/util.py
langgraph/checkpoint/test_redis/version.py
langgraph/store/redis/__init__.py
langgraph/store/redis/aio.py
langgraph/store/redis/base.py
langgraph/store/redis/py.typed
langgraph/store/redis/token_unescaper.py
langgraph/store/redis/types.py
test_langgraph_checkpoint_redis-0.3.2.dist-info/METADATA
test_langgraph_checkpoint_redis-0.3.2.dist-info/WHEEL
test_langgraph_checkpoint_redis-0.3.2.dist-info/entry_points.txt
test_langgraph_checkpoint_redis-0.3.2.dist-info/licenses/LICENSE
test_langgraph_checkpoint_redis-0.3.2.dist-info/RECORD
