Metadata-Version: 2.4
Name: test-langgraph-checkpoint-redis
Version: 0.3.2
Summary: Redis implementation of the LangGraph agent checkpoint saver and store.
Project-URL: Repository, https://www.github.com/redis-developer/langgraph-redis
Author-email: "Redis Inc." <applied.ai@redis.com>, Brian Sam-Bodden <bsb@redis.io>
License: MIT
License-File: LICENSE
Keywords: agents,ai,langchain,langgraph,redis,redis-client,vector-database
Classifier: License :: OSI Approved :: MIT License
Classifier: Programming Language :: Python :: 3.10
Classifier: Programming Language :: Python :: 3.11
Classifier: Programming Language :: Python :: 3.12
Classifier: Programming Language :: Python :: 3.13
Requires-Python: <3.14,>=3.10
Requires-Dist: langgraph-checkpoint<4.0.0,>=3.0.0
Requires-Dist: orjson>=3.9.0
Requires-Dist: redis>=5.2.1
Requires-Dist: redisvl<1.0.0,>=0.11.0
Requires-Dist: tomli>=2.0.1; python_version < '3.11'
Provides-Extra: dev
Requires-Dist: aioconsole>=0.8.1; extra == 'dev'
Requires-Dist: aiofiles>=24.1.0; extra == 'dev'
Requires-Dist: anyio>=4.10.0; extra == 'dev'
Requires-Dist: black>=25.1.0; extra == 'dev'
Requires-Dist: codespell>=2.4.1; extra == 'dev'
Requires-Dist: coverage>=7.10.3; extra == 'dev'
Requires-Dist: cryptography>=44.0.1; (python_version > '3.9.1') and extra == 'dev'
Requires-Dist: isort>=6.0.1; extra == 'dev'
Requires-Dist: langchain-openai>=0.3.30; extra == 'dev'
Requires-Dist: langgraph>=0.3.0; extra == 'dev'
Requires-Dist: langmem>=0.0.30; extra == 'dev'
Requires-Dist: mypy<2,>=1.11.0; extra == 'dev'
Requires-Dist: pympler>=1.1; extra == 'dev'
Requires-Dist: pytest-asyncio>=1.1.0; extra == 'dev'
Requires-Dist: pytest-cov>=6.2.1; extra == 'dev'
Requires-Dist: pytest-mock>=3.14.1; extra == 'dev'
Requires-Dist: pytest-xdist[psutil]>=3.8.0; extra == 'dev'
Requires-Dist: pytest>=8.4.1; extra == 'dev'
Requires-Dist: testcontainers>=4.12.0; extra == 'dev'
Requires-Dist: vulture>=2.14; extra == 'dev'
